declutrr/app.py
declutrr/constants.py
declutrr/file_manager.py
declutrr/image_processor.py
declutrr/utils.py
declutrr-0.1.4.dist-info/LICENSE
declutrr-0.1.4.dist-info/METADATA
declutrr-0.1.4.dist-info/WHEEL
declutrr-0.1.4.dist-info/entry_points.txt
declutrr-0.1.4.dist-info/RECORD
