Metadata-Version: 2.1
Name: declutrr
Version: 0.1.4
Summary: A Date-app-like interface for rapidly sorting photos
Home-page: https://github.com/vmatt/declutrr
License: MIT
Author: Mate Valko
Author-email: declutrr@valq.hu
Requires-Python: >=3.10,<4.0
Classifier: Development Status :: 4 - Beta
Classifier: Environment :: X11 Applications :: GTK
Classifier: Intended Audience :: Developers
Classifier: Intended Audience :: End Users/Desktop
Classifier: License :: OSI Approved :: MIT License
Classifier: Operating System :: OS Independent
Classifier: Programming Language :: Python :: 3
Classifier: Programming Language :: Python :: 3.10
Classifier: Programming Language :: Python :: 3.11
Classifier: Programming Language :: Python :: 3.12
Classifier: Programming Language :: Python :: 3.13
Classifier: Topic :: Desktop Environment :: File Managers
Classifier: Topic :: Multimedia :: Graphics
Classifier: Topic :: Utilities
Provides-Extra: tools
Requires-Dist: Pillow (>=11.0.0,<12.0.0)
Project-URL: Documentation, https://github.com/vmatt/declutrr/wiki
Project-URL: Repository, https://github.com/vmatt/declutrr
